Metadata-Version: 2.1
Name: EasyBlackjack
Version: 0.1.6
Summary: A Single-Deck Blackjack hand generator and calculator
Home-page: https://github.com/antogno/easyblackjack
Author: Antonio Granaldi
Author-email: tonio.granaldi@gmail.com
License: UNKNOWN
Platform: UNKNOWN
Classifier: Programming Language :: Python :: 3
Classifier: License :: CC0 1.0 Universal (CC0 1.0) Public Domain Dedication
Classifier: Operating System :: OS Independent
License-File: LICENSE
